Workbook

Sheet Sales Data
A1: SuperMart Retail Store - Monthly Sales Data (2024)
A2: Case Study: Analyzing sales performance across departments and regions | Data Interpretation Project
A3: S.No | B3: Salesperson | C3: Region | D3: Department | E3: Units Sold | F3: Unit Price (Rs.) | G3: Total Sales (Rs.) | H3: Discount (%) | I3: Net Sales (Rs.) | J3: Month
A4: 1 | B4: Amit Sharma | C4: North | D4: Electronics | E4: 120 | F4: 15000 | G4: =E4*F4 -> 1800000 | H4: 5 | I4: =G4*(1-H4/100) -> 1710000 | J4: January
A5: 2 | B5: Priya Singh | C5: South | D5: Clothing | E5: 200 | F5: 1200 | G5: =E5*F5 -> 240000 | H5: 10 | I5: =G5*(1-H5/100) -> 216000 | J5: January
A6: 3 | B6: Ravi Kumar | C6: East | D6: Groceries | E6: 500 | F6: 80 | G6: =E6*F6 -> 40000 | H6: 2 | I6: =G6*(1-H6/100) -> 39200 | J6: February
A7: 4 | B7: Sunita Verma | C7: West | D7: Electronics | E7: 85 | F7: 22000 | G7: =E7*F7 -> 1870000 | H7: 8 | I7: =G7*(1-H7/100) -> 1720400 | J7: February
A8: 5 | B8: Deepak Joshi | C8: North | D8: Furniture | E8: 60 | F8: 8500 | G8: =E8*F8 -> 510000 | H8: 12 | I8: =G8*(1-H8/100) -> 448800 | J8: March
A9: 6 | B9: Meena Rao | C9: South | D9: Groceries | E9: 650 | F9: 95 | G9: =E9*F9 -> 61750 | H9: 3 | I9: =G9*(1-H9/100) -> 59897.5 | J9: March
A10: 7 | B10: Karan Mehta | C10: East | D10: Clothing | E10: 180 | F10: 1500 | G10: =E10*F10 -> 270000 | H10: 7 | I10: =G10*(1-H10/100) -> 251100 | J10: April
A11: 8 | B11: Anjali Gupta | C11: West | D11: Electronics | E11: 95 | F11: 18000 | G11: =E11*F11 -> 1710000 | H11: 6 | I11: =G11*(1-H11/100) -> 1607400 | J11: April
A12: 9 | B12: Sanjay Patel | C12: North | D12: Furniture | E12: 45 | F12: 12000 | G12: =E12*F12 -> 540000 | H12: 15 | I12: =G12*(1-H12/100) -> 459000 | J12: May
A13: 10 | B13: Pooja Nair | C13: South | D13: Electronics | E13: 110 | F13: 16500 | G13: =E13*F13 -> 1815000 | H13: 4 | I13: =G13*(1-H13/100) -> 1742400 | J13: May
A14: 11 | B14: Vikram Singh | C14: East | D14: Groceries | E14: 720 | F14: 75 | G14: =E14*F14 -> 54000 | H14: 1 | I14: =G14*(1-H14/100) -> 53460 | J14: June
A15: 12 | B15: Rekha Mishra | C15: West | D15: Clothing | E15: 160 | F15: 1800 | G15: =E15*F15 -> 288000 | H15: 9 | I15: =G15*(1-H15/100) -> 262080 | J15: June
... A21: 18 | B21: Divya Pillai | C21: South | D21: Electronics | E21: 130 | F21: 17500 | G21: =E21*F21 -> 2275000 | H21: 7 | I21: =G21*(1-H21/100) -> 2115750 | J21: September
B22: TOTAL | E22: =SUM(E4:E21) -> 4010 | G22: =SUM(G4:G21) -> 15616450 | I22: =SUM(I4:I21) -> 14545008

Sheet Analysis & Formulas
A1: Data Analysis - 10 Excel Functions Applied to Sales Data
A2: # | B2: Function | C2: Formula Written | D2: Result | E2: Interpretation
A3: 1 | B3: SUM | C3: =SUM('Sales Data'!I4:I21) -> 14545008 | D3: =SUM('Sales Data'!I4:I21) -> 14545008 | E3: Adds all 18 net sales values to get total store revenue
A4: 2 | B4: AVERAGE | C4: =AVERAGE('Sales Data'!E4:E21) -> 222.77778 | D4: =AVERAGE('Sales Data'!E4:E21) -> 222.77778 | E4: Finds average units sold per salesperson across all records
A5: 3 | B5: MAX | C5: =MAX('Sales Data'!I4:I21) -> 2660000 | D5: =MAX('Sales Data'!I4:I21) -> 2660000 | E5: Returns the single highest net sale amount in the dataset
A6: 4 | B6: MIN | C6: =MIN('Sales Data'!I4:I21) -> 39200 | D6: =MIN('Sales Data'!I4:I21) -> 39200 | E6: Returns the single lowest net sale amount in the dataset
A7: 5 | B7: COUNT | C7: =COUNT('Sales Data'!E4:E21) -> 18 | D7: =COUNT('Sales Data'!E4:E21) -> 18 | E7: Counts how many numeric entries exist in Units Sold column
A8: 6 | B8: COUNTIF | C8: =COUNTIF('Sales Data'!C4:C21,"North") -> 5 | D8: =COUNTIF('Sales Data'!C4:C21,"North") -> 5 | E8: Counts only the rows where Region equals North
A9: 7 | B9: SUMIF | C9: =SUMIF('Sales Data'!D4:D21,"Electronics",'Sales Data'!I4:I21) -> 11555950 | D9: =SUMIF('Sales Data'!D4:D21,"Electronics",'Sales Data'!I4:I21) -> 11555950 | E9: Sums Net Sales for Electronics department only
A10: 8 | B10: IF | C10: =IF(SUM('Sales Data'!I4:I21)>2000000,"TARGET MET","BELOW TARGET") -> TARGET MET | D10: =IF(SUM('Sales Data'!I4:I21)>2000000,"TARGET MET","BELOW TARGET") -> TARGET MET | E10: Checks if total revenue crosses Rs. 20 lakh target
A11: 9 | B11: VLOOKUP | C11: =VLOOKUP(7,'Sales Data'!A4:I21,9,FALSE()) -> 251100 | D11: =VLOOKUP(7,'Sales Data'!A4:I21,9,FALSE()) -> 251100 | E11: Looks up Salesperson #7 and retrieves their Net Sales value
A12: 10 | B12: AVERAGEIF | C12: =AVERAGEIF('Sales Data'!C4:C21,"South",'Sales Data'!E4:E21) -> 229 | D12: =AVERAGEIF('Sales Data'!C4:C21,"South",'Sales Data'!E4:E21) -> 229 | E12: Calculates average units sold specifically for South region

Sheet Summary Dashboard
A1: SuperMart - Executive Summary Dashboard
A2: KEY PERFORMANCE INDICATORS
A3: Total Revenue (Rs.) | D3: Avg Net Sales/Deal
A4: =SUM('Sales Data'!I4:I21) -> 14545008 | D4: =AVERAGE('Sales Data'!I4:I21) -> 808056.03
A7: Max Single Sale (Rs.) | D7: Min Single Sale (Rs.)
A8: =MAX('Sales Data'!I4:I21) -> 2660000 | D8: =MIN('Sales Data'!I4:I21) -> 39200
A11: Total Units Sold | D11: No. of Transactions
A12: =SUM('Sales Data'!E4:E21) -> 4010 | D12: =COUNT('Sales Data'!E4:E21) -> 18
A15: Electronics Revenue | D15: North Region Sales
A16: =SUMIF('Sales Data'!D4:D21,"Electronics",'Sales Data'!I4:I21) -> 11555950 | D16: =SUMIF('Sales Data'!C4:C21,"North",'Sales Data'!I4:I21) -> 5752820
A19: REGION-WISE PERFORMANCE BREAKDOWN
A20: Region | B20: Total Net Sales | C20: Units Sold | D20: Avg Discount (%) | E20: Records | F20: Target Status
A21: North | B21: =SUMIF('Sales Data'!C4:C21,"North",'Sales Data'!I4:I21) -> 5752820 | C21: =SUMIF('Sales Data'!C4:C21,"North",'Sales Data'!E4:E21) -> 435 | D21: =AVERAGEIF('Sales Data'!C4:C21,"North",'Sales Data'!H4:H21) -> 10 | E21: =COUNTIF('Sales Data'!C4:C21,"North") -> 5 | F21: =IF(SUMIF('Sales Data'!C4:C21,"North",'Sales Data'!I4:I21)>500000,"STRONG","MODERATE") -> STRONG
A22: South | B22: =SUMIF('Sales Data'!C4:C21,"South",'Sales Data'!I4:I21) -> 4599072.5 | C22: =SUMIF('Sales Data'!C4:C21,"South",'Sales Data'!E4:E21) -> 1145 | D22: =AVERAGEIF('Sales Data'!C4:C21,"South",'Sales Data'!H4:H21) -> 7 | E22: =COUNTIF('Sales Data'!C4:C21,"South") -> 5 | F22: =IF(SUMIF('Sales Data'!C4:C21,"South",'Sales Data'!I4:I21)>500000,"STRONG","MODERATE") -> STRONG
A23: East | B23: =SUMIF('Sales Data'!C4:C21,"East",'Sales Data'!I4:I21) -> 560900 | C23: =SUMIF('Sales Data'!C4:C21,"East",'Sales Data'!E4:E21) -> 1610 | D23: =AVERAGEIF('Sales Data'!C4:C21,"East",'Sales Data'!H4:H21) -> 4 | E23: =COUNTIF('Sales Data'!C4:C21,"East") -> 4 | F23: =IF(SUMIF('Sales Data'!C4:C21,"East",'Sales Data'!I4:I21)>500000,"STRONG","MODERATE") -> STRONG
A24: West | B24: =SUMIF('Sales Data'!C4:C21,"West",'Sales Data'!I4:I21) -> 3632216 | C24: =SUMIF('Sales Data'!C4:C21,"West",'Sales Data'!E4:E21) -> 820 | D24: =AVERAGEIF('Sales Data'!C4:C21,"West",'Sales Data'!H4:H21) -> 6.25 | E24: =COUNTIF('Sales Data'!C4:C21,"West") -> 4 | F24: =IF(SUMIF('Sales Data'!C4:C21,"West",'Sales Data'!I4:I21)>500000,"STRONG","MODERATE") -> STRONG
